.bumpversion.cfg
.coveragerc
.editorconfig
.readthedocs.yml
AUTHORS.rst
DebateWiki/__init__.py
DebateWiki/__main__.py
DebateWiki/app.py
DebateWiki/cli/__init__.py
DebateWiki/cli/start.py
DebateWiki/exceptions.py
DebateWiki/schemas.py
docs/conf.py
docs/index.rst
docs/make.bat
docs/Makefile
MANIFEST.in
poetry.lock
tox.ini
debatewiki-0.1.0a0.dist-info/entry_points.txt
debatewiki-0.1.0a0.dist-info/LICENSE
debatewiki-0.1.0a0.dist-info/WHEEL
debatewiki-0.1.0a0.dist-info/METADATA
debatewiki-0.1.0a0.dist-info/RECORD
